{
  "ned-mar": {
    "at": "2026-07-09T15:41:07",
    "adj": -0.7393874516160156
  },
  "civ-nor": {
    "at": "2026-07-09T15:41:07",
    "adj": 0.0
  },
  "fra-swe": {
    "at": "2026-07-09T15:41:07",
    "adj": 0.7393874516160156
  },
  "mex-ecu": {
    "at": "2026-07-09T15:41:07",
    "adj": 0.7393874516160156
  },
  "eng-cod": {
    "at": "2026-07-09T15:41:07",
    "adj": -0.7393874516160156
  },
  "bel-sen": {
    "at": "2026-07-09T15:41:07",
    "adj": 0.0
  },
  "usa-bih": {
    "at": "2026-07-09T15:41:07",
    "adj": 0.0
  },
  "esp-aut": {
    "at": "2026-07-09T15:41:07",
    "adj": 0.7393874516160156
  },
  "por-cro": {
    "at": "2026-07-09T15:41:07",
    "adj": 0.0
  },
  "sui-dza": {
    "at": "2026-07-09T15:41:07",
    "adj": 0.7393874516160156
  },
  "aus-egy": {
    "at": "2026-07-09T15:41:07",
    "adj": 0.0
  },
  "arg-cpv": {
    "at": "2026-07-09T15:41:07",
    "adj": -1.2185506495292238
  },
  "col-gha": {
    "at": "2026-07-09T15:41:07",
    "adj": -0.7393874516160156
  },
  "can-mar": {
    "at": "2026-07-09T15:41:07",
    "adj": -1.2185506495292238
  },
  "par-fra": {
    "at": "2026-07-09T15:41:07",
    "adj": 0.7393874516160156
  },
  "fra-mar": {
    "at": "2026-07-09T22:47:42",
    "adj": 0.7393874516160156
  },
  "esp-bel": {
    "at": "2026-07-10T21:31:49",
    "adj": 0.0
  },
  "nor-eng": {
    "at": "2026-07-12T07:48:39",
    "adj": 0.0
  },
  "arg-sui": {
    "at": "2026-07-12T07:48:39",
    "adj": 0.7393874516160156
  },
  "fra-esp": {
    "at": "2026-07-14T23:36:46",
    "adj": -1.2185506495292238
  }
}